beijing_time_mcp/__init__.py
beijing_time_mcp/server.py
beijing_time_mcp-0.1.2.dist-info/licenses/LICENSE
beijing_time_mcp-0.1.2.dist-info/METADATA
beijing_time_mcp-0.1.2.dist-info/WHEEL
beijing_time_mcp-0.1.2.dist-info/entry_points.txt
beijing_time_mcp-0.1.2.dist-info/top_level.txt
beijing_time_mcp-0.1.2.dist-info/RECORD
