Metadata-Version: 2.4
Name: beijing-time-mcp
Version: 0.1.2
Summary: MCP server for querying Beijing time
Author-email: Archer Liu <archer@example.com>
License: MIT
Project-URL: Homepage, https://github.com/archerliu/beijing-time-mcp
Project-URL: Repository, https://github.com/archerliu/beijing-time-mcp
Project-URL: Issues, https://github.com/archerliu/beijing-time-mcp/issues
Keywords: mcp,time,beijing,server
Classifier: Development Status :: 4 - Beta
Classifier: Intended Audience :: Developers
Classifier: License :: OSI Approved :: MIT License
Classifier: Programming Language :: Python :: 3
Classifier: Programming Language :: Python :: 3.8
Classifier: Programming Language :: Python :: 3.9
Classifier: Programming Language :: Python :: 3.10
Classifier: Programming Language :: Python :: 3.11
Classifier: Programming Language :: Python :: 3.12
Requires-Python: >=3.8
License-File: LICENSE
Requires-Dist: mcp>=1.0.0
Requires-Dist: pytz>=2023.3
Provides-Extra: dev
Requires-Dist: pytest>=7.0.0; extra == "dev"
Requires-Dist: pytest-asyncio>=0.21.0; extra == "dev"
Requires-Dist: black>=23.0.0; extra == "dev"
Requires-Dist: isort>=5.12.0; extra == "dev"
Requires-Dist: flake8>=6.0.0; extra == "dev"
Requires-Dist: mypy>=1.0.0; extra == "dev"
Dynamic: license-file
